utran/__init__.py
utran/__main__.py
utran/cli/__init__.py
utran/cli/build.py
utran/cli/command.py
utran/cli/utils.py
utran/core/__init__.py
utran/core/context.py
utran/core/host.py
utran/core/ipc.py
utran/core/schedule.py
utran/core/backend/__init__.py
utran/core/backend/aiohttp_backend.py
utran/core/backend/base.py
utran/core/backend/fastapi_backend.py
utran/core/backend/ut_backend.py
utran/core/general/__init__.py
utran/core/general/base_action.py
utran/core/general/baseclass.py
utran/core/general/caches.py
utran/core/general/event_protocol.py
utran/core/general/exceptions.py
utran/core/general/future.py
utran/core/general/message_protocol.py
utran/core/general/utils.py
utran/core/local/__init__.py
utran/core/local/action.py
utran/core/remote/__init__.py
utran/core/remote/action.py
utran/core/remote/wokeblock.py
utran/core/remote/worker.py
utran/log/__init__.py
utran/py_ts/__init__.py
utran/py_ts/clf.py
utran/py_ts/type_map.py
utran/socket/__init__.py
utran/socket/base.py
utran/socket/client.py
utran/socket/sever.py
utran/socket/utils.py
utran-2.0.1.dist-info/LICENSE
utran-2.0.1.dist-info/METADATA
utran-2.0.1.dist-info/WHEEL
utran-2.0.1.dist-info/entry_points.txt
utran-2.0.1.dist-info/top_level.txt
utran-2.0.1.dist-info/RECORD
