Metadata-Version: 2.1
Name: utran
Version: 2.0.1
Summary: Utran is a powerful rpc application
Home-page: https://utran.host
Author: utran
Author-email: utran.host@qq.com
License: MIT License
Keywords: RPC,utran
Platform: any
License-File: LICENSE
Requires-Dist: click
Requires-Dist: cachetools
Requires-Dist: loguru
